MANIFEST.in
README.md
setup.py
dash_large_upload/Upload.py
dash_large_upload/__init__.py
dash_large_upload/_imports_.py
dash_large_upload/dash_large_upload.dev.js
dash_large_upload/dash_large_upload.min.js
dash_large_upload/dash_large_upload.py
dash_large_upload/metadata.json
dash_large_upload/package.json
dash_large_upload.egg-info/PKG-INFO
dash_large_upload.egg-info/SOURCES.txt
dash_large_upload.egg-info/dependency_links.txt
dash_large_upload.egg-info/top_level.txt