Metadata-Version: 1.0
Name: dash-large-upload
Version: 0.0.4
Summary: Upload of large files for Dash
Home-page: UNKNOWN
Author: tracek lukasz.tracewski@outlook.com
Author-email: UNKNOWN
License: MIT
Platform: UNKNOWN
